javanicus.py
setup.py
Javanicus.egg-info/PKG-INFO
Javanicus.egg-info/SOURCES.txt
Javanicus.egg-info/dependency_links.txt
Javanicus.egg-info/entry_points.txt
Javanicus.egg-info/requires.txt
Javanicus.egg-info/top_level.txt