Metadata-Version: 1.1
Name: Javanicus
Version: 0.1
Summary: A WebHDFS FUSE driver
Home-page: http://github.com/rascalking/javanicus
Author: David Bonner
Author-email: dbonner@gmail.com
License: GPLv3
Platform: UNKNOWN
Classifier: Development Status :: 4 - Beta
Classifier: Environment :: Console
Classifier: Environment :: No Input/Output (Daemon)
Classifier: License :: OSI Approved :: GNU General Public License v3 (GPLv3)
Classifier: Operating System :: MacOS :: MacOS X
Classifier: Operating System :: POSIX :: Linux
Classifier: Programming Language :: Python :: 2.6
Classifier: Programming Language :: Python :: 2.7
Classifier: Topic :: System :: Distributed Computing
Classifier: Topic :: System :: Filesystems
